hello_wolf_software/__init__.py
hello_wolf_software/hello.py
hello_wolf_software-0.0.3.dist-info/LICENSE.md
hello_wolf_software-0.0.3.dist-info/METADATA
hello_wolf_software-0.0.3.dist-info/WHEEL
hello_wolf_software-0.0.3.dist-info/entry_points.txt
hello_wolf_software-0.0.3.dist-info/top_level.txt
hello_wolf_software-0.0.3.dist-info/RECORD
