Metadata-Version: 2.1
Name: hello-wolf-software
Version: 0.0.3
Summary: A simple hello world test
Home-page: https://github.com/DevelopersToolbox/hello-wolf-software
Author: Wolf Software
Author-email: pypi@wolfsoftware.com
Classifier: Programming Language :: Python :: 3
Classifier: License :: OSI Approved :: MIT License
Classifier: Operating System :: OS Independent
Requires-Python: >=3.6
License-File: LICENSE.md
